README.rst
setup.py
./__init__.py
./cot.py
./iibb.py
./nsis.py
./padron.py
./php.py
./pyafipws.py
./pyemail.py
./pyfepdf.py
./pyi25.py
./pyrece.py
./pyrece.rsrc.py
./rece.py
./rece1.py
./receb.py
./receb1.py
./recem.py
./recex.py
./recex1.py
./rg3685.py
./sired.py
./soap.py
./trazafito.py
./trazamed.py
./trazarenpre.py
./trazavet.py
./utils.py
./wdigdepfiel.py
./wsaa.py
./wsbfe.py
./wsbfev1.py
./wscdc.py
./wscoc.py
./wsctgv3.py
./wsfe.py
./wsfev1.py
./wsfex.py
./wsfexv1.py
./wslpg.py
./wslpg_datos.py
./wsltv.py
./wsmtx.py
PyAfipWs.egg-info/PKG-INFO
PyAfipWs.egg-info/SOURCES.txt
PyAfipWs.egg-info/dependency_links.txt
PyAfipWs.egg-info/top_level.txt