Metadata-Version: 1.1
Name: PyAfipWs
Version: 2.7.1859
Summary: Interfases, tools and apps for Argentina's gov't. webservices (soap, com/dll, pdf, dbf, xml, etc.)
Home-page: http://www.sistemasagiles.com.ar
Author: Mariano Reingart
Author-email: reingart@gmail.com
License: GNU GPL v3
Keywords: webservice electronic invoice pdf traceability
Platform: UNKNOWN
Classifier: Development Status :: 5 - Production/Stable
Classifier: Intended Audience :: Developers
Classifier: Intended Audience :: End Users/Desktop
Classifier: Intended Audience :: Financial and Insurance Industry
Classifier: License :: OSI Approved :: GNU General Public License v3 (GPLv3)
Classifier: Programming Language :: Python
Classifier: Programming Language :: Python :: 2.5
Classifier: Programming Language :: Python :: 2.6
Classifier: Programming Language :: Python :: 2.7
Classifier: Operating System :: OS Independent
Classifier: Operating System :: Microsoft :: Windows
Classifier: Natural Language :: Spanish
Classifier: Topic :: Office/Business :: Financial :: Point-Of-Sale
Classifier: Topic :: Software Development :: Libraries :: Python Modules
Classifier: Topic :: Software Development :: Object Brokering
